[
  {
    "disease_name": "单纯疱疹",
    "aliases": ["热疮", "herpes simplex", "火燎疮"],
    "overview": "单纯疱疹是由单纯疱疹病毒（HSV）感染引起的复发性皮肤病，好发于皮肤黏膜交界处，易复发。",
    "symptoms": ["簇集性小水疱", "灼热刺痛", "糜烂结痂", "反复发作", "淋巴结肿大"],
    "causes": ["HSV-1型（口唇）", "HSV-2型（生殖器）", "免疫力下降", "发热", "紫外线照射", "精神紧张"],
    "treatment": ["抗病毒药物（阿昔洛韦）", "外用抗病毒软膏", "镇痛药物", "免疫调节剂", "光疗"],
    "precautions": ["避免接触传染", "增强免疫力", "防晒", "避免精神紧张", "复发时避免性生活"],
    "severity": "mild",
    "department": "皮肤科",
    "common_population": ["各年龄段", "免疫力低下者", "经常日晒者"],
    "related_diseases": ["带状疱疹", "生殖器疱疹", "疱疹性龈口炎"]
  },
  {
    "disease_name": "水痘",
    "aliases": ["chickenpox", "varicella"],
    "overview": "水痘是由水痘-带状疱疹病毒引起的急性呼吸道传染病，以全身同时出现丘疹、水疱及结痂为特征，好发于儿童。",
    "symptoms": ["全身丘疹", "水疱", "结痂", "瘙痒", "低热", "头痛", "食欲不振"],
    "causes": ["水痘-带状疱疹病毒感染", "呼吸道传播", "接触传播", "免疫力低下", "未接种疫苗"],
    "treatment": ["抗病毒药物（阿昔洛韦）", "对症治疗", "止痒药物", "预防感染", "隔离治疗"],
    "precautions": ["接种疫苗", "隔离患者", "避免接触", "增强免疫力", "保持皮肤清洁"],
    "severity": "moderate",
    "department": "皮肤科/儿科",
    "common_population": ["儿童", "未接种疫苗者", "免疫力低下者"],
    "related_diseases": ["带状疱疹", "水痘脑炎", "水痘肺炎"]
  },
  {
    "disease_name": "带状疱疹",
    "aliases": ["蛇串疮", "缠腰龙", "herpes zoster"],
    "overview": "带状疱疹是由水痘-带状疱疹病毒再激活引起的急性感染性皮肤病，特征为沿身体单侧体表神经分布的成簇水疱，伴有明显的神经痛。",
    "symptoms": ["沿神经分布的簇集性水疱", "剧烈神经痛", "局部皮肤灼热", "红斑、丘疹", "水疱清亮或混浊", "局部淋巴结肿大"],
    "causes": ["水痘-带状疱疹病毒再激活", "免疫力下降", "年龄增长（50岁以上高发）", "精神压力大", "慢性疾病", "免疫抑制治疗"],
    "treatment": ["抗病毒药物（阿昔洛韦、伐昔洛韦）", "镇痛药物（加巴喷丁）", "糖皮质激素（早期）", "营养神经药物", "局部外用药"],
    "precautions": ["发病72小时内尽早治疗", "避免抓破水疱", "保持患处清洁", "穿宽松衣物", "避免接触孕妇和婴幼儿"],
    "severity": "moderate_to_severe",
    "department": "皮肤科",
    "common_population": ["50岁以上老年人", "免疫力低下者", "慢性疾病患者", "女性略多于男性"],
    "related_diseases": ["带状疱疹后神经痛", "眼带状疱疹", "Ramsay-Hunt综合征"]
  },
  {
    "disease_name": "寻常疣",
    "aliases": ["瘊子", "verruca vulgaris", "刺瘊"],
    "overview": "寻常疣是由人乳头瘤病毒（HPV）感染引起的良性皮肤赘生物，好发于手指、手背等暴露部位。",
    "symptoms": ["角化性丘疹", "表面粗糙", "灰黄或污褐色", "黑点（血栓毛细血管）", "数目不等"],
    "causes": ["HPV-2、4型感染", "皮肤破损", "免疫力低下", "直接接触传播", "自体接种"],
    "treatment": ["冷冻治疗", "激光治疗", "电灼治疗", "外用维A酸", "光动力治疗", "免疫调节剂"],
    "precautions": ["避免搔抓", "避免共用物品", "保持皮肤干燥", "增强免疫力", "及时治疗"],
    "severity": "mild",
    "department": "皮肤科",
    "common_population": ["儿童和青少年", "免疫力低下者", "经常接触水者"],
    "related_diseases": ["扁平疣", "跖疣", "尖锐湿疣"]
  },
  {
    "disease_name": "扁平疣",
    "aliases": ["扁瘊", "verruca plana"],
    "overview": "扁平疣是由人乳头瘤病毒（HPV）感染引起的扁平丘疹，好发于面部和手背，多见于青少年。",
    "symptoms": ["扁平丘疹", "肤色或淡褐色", "表面光滑", "同形反应", "轻度瘙痒"],
    "causes": ["HPV-3、10型感染", "免疫力低下", "皮肤破损", "直接接触传播"],
    "treatment": ["外用维A酸", "冷冻治疗", "激光治疗", "光动力治疗", "免疫调节剂", "中药治疗"],
    "precautions": ["避免搔抓（防止同形反应）", "避免摩擦", "增强免疫力", "不共用毛巾", "防晒"],
    "severity": "mild",
    "department": "皮肤科",
    "common_population": ["青少年", "女性较多", "免疫力低下者"],
    "related_diseases": ["寻常疣", "痤疮", "脂溢性角化病"]
  },
  {
    "disease_name": "跖疣",
    "aliases": ["足底疣", "verruca plantaris"],
    "overview": "跖疣是发生于足底的寻常疣，由HPV感染引起，因受压而向皮内生长，行走时疼痛明显。",
    "symptoms": ["足底角化性斑块", "表面粗糙", "黑点", "压痛明显", "多发或单发"],
    "causes": ["HPV-1型感染", "足底受压", "多汗", "免疫力低下", "公共场所赤足"],
    "treatment": ["冷冻治疗", "激光治疗", "外用维A酸", "水杨酸制剂", "光动力治疗", "手术切除"],
    "precautions": ["穿宽松鞋袜", "保持足部干燥", "公共场所穿拖鞋", "避免搔抓", "增强免疫力"],
    "severity": "mild",
    "department": "皮肤科",
    "common_population": ["青少年", "运动员", "多汗者", "免疫力低下者"],
    "related_diseases": ["鸡眼", "胼胝", "寻常疣"]
  },
  {
    "disease_name": "传染性软疣",
    "aliases": ["水瘊子", "molluscum contagiosum"],
    "overview": "传染性软疣是由痘病毒感染引起的传染性皮肤病，特征为蜡样光泽的半球形丘疹，中央有脐凹。",
    "symptoms": ["半球形丘疹", "蜡样光泽", "中央脐凹", "乳白色", "可挤出乳酪样物质"],
    "causes": ["痘病毒感染", "直接接触传播", "自体接种", "免疫力低下", "游泳池传播"],
    "treatment": ["刮除术", "冷冻治疗", "激光治疗", "外用维A酸", "免疫调节剂", "自愈"],
    "precautions": ["避免搔抓", "避免共用毛巾", "游泳池注意卫生", "增强免疫力", "隔离治疗"],
    "severity": "mild",
    "department": "皮肤科",
    "common_population": ["儿童", "免疫功能低下者", "性活跃成年人", "湿疹患者"],
    "related_diseases": ["寻常疣", "扁平疣", "毛囊炎"]
  },
  {
    "disease_name": "手足口病",
    "aliases": ["hand, foot and mouth disease", "HFMD"],
    "overview": "手足口病是由肠道病毒引起的急性传染病，以手、足、口腔等部位出现疱疹或溃疡为特征，多见于婴幼儿。",
    "symptoms": ["手、足、口腔疱疹", "低热", "食欲不振", "口腔溃疡疼痛", "臀部皮疹"],
    "causes": ["柯萨奇病毒A16型", "肠道病毒71型", "密切接触传播", "粪-口传播", "呼吸道传播"],
    "treatment": ["对症治疗", "退热", "口腔护理", "抗病毒治疗", "隔离治疗", "补液"],
    "precautions": ["勤洗手", "隔离患儿", "消毒玩具用具", "避免去人群密集处", "注意食品卫生"],
    "severity": "mild_to_moderate",
    "department": "儿科/皮肤科",
    "common_population": ["5岁以下儿童", "托幼机构儿童", "免疫力低下者"],
    "related_diseases": ["疱疹性咽峡炎", "水痘", "麻疹"]
  },
  {
    "disease_name": "脓疱疮",
    "aliases": ["黄水疮", "impetigo", "脓痂疹"],
    "overview": "脓疱疮是由金黄色葡萄球菌或溶血性链球菌引起的急性化脓性皮肤病，具有接触传染性，多见于儿童。",
    "symptoms": ["脓疱", "蜜黄色痂皮", "红斑", "瘙痒", "接触传染"],
    "causes": ["金黄色葡萄球菌感染", "溶血性链球菌感染", "皮肤屏障受损", "卫生条件差", "密切接触传播"],
    "treatment": ["外用抗生素软膏（莫匹罗星）", "口服抗生素（头孢类）", "局部清洁消毒", "隔离治疗"],
    "precautions": ["保持皮肤清洁", "避免搔抓", "隔离患儿", "消毒衣物用具", "剪短指甲"],
    "severity": "mild",
    "department": "皮肤科",
    "common_population": ["2-5岁儿童", "卫生条件差者", "热带地区居民"],
    "related_diseases": ["湿疹", "痱子", "链球菌感染"]
  },
  {
    "disease_name": "毛囊炎",
    "aliases": ["folliculitis", "疖", "痈"],
    "overview": "毛囊炎是毛囊的炎症反应，可由细菌、真菌、病毒或物理因素引起，表现为毛囊周围的红色丘疹或脓疱。",
    "symptoms": ["红色丘疹", "脓疱", "疼痛", "瘙痒", "毛发周围红肿"],
    "causes": ["金黄色葡萄球菌感染", "真菌感染（马拉色菌）", "物理刺激", "免疫力低下", "糖尿病", "长期使用激素"],
    "treatment": ["外用抗生素", "外用抗真菌药", "口服抗生素", "光动力治疗", "激光治疗"],
    "precautions": ["保持皮肤清洁", "避免搔抓", "不共用剃须刀", "控制血糖", "增强免疫力"],
    "severity": "mild",
    "department": "皮肤科",
    "common_population": ["成年人", "糖尿病患者", "免疫力低下者", "剃须者"],
    "related_diseases": ["痤疮", "疖肿", "糖尿病"]
  },
  {
    "disease_name": "丹毒",
    "aliases": ["erysipelas", "流火", "腿游风"],
    "overview": "丹毒是由溶血性链球菌感染引起的急性真皮浅层淋巴管炎，表现为境界清楚的水肿性红斑，伴有发热等全身症状。",
    "symptoms": ["境界清楚的红斑", "水肿", "灼热疼痛", "高热", "寒战", "淋巴结肿大"],
    "causes": ["A组β溶血性链球菌感染", "足癣继发感染", "皮肤破损", "免疫力低下", "淋巴回流障碍"],
    "treatment": ["青霉素类抗生素", "头孢类抗生素", "大环内酯类抗生素", "卧床休息", "抬高患肢"],
    "precautions": ["积极治疗足癣", "避免皮肤破损", "保持皮肤清洁", "及时治疗小伤口", "预防复发"],
    "severity": "moderate",
    "department": "皮肤科",
    "common_population": ["中老年人", "足癣患者", "淋巴水肿患者", "免疫力低下者"],
    "related_diseases": ["蜂窝织炎", "足癣", "淋巴水肿", "糖尿病"]
  },
  {
    "disease_name": "蜂窝织炎",
    "aliases": ["cellulitis", "皮下组织感染"],
    "overview": "蜂窝织炎是皮下组织的弥漫性化脓性感染，由细菌侵入皮下脂肪层引起，病变范围较丹毒更深更广。",
    "symptoms": ["弥漫性红肿", "疼痛", "皮温升高", "发热", "寒战", "白细胞升高"],
    "causes": ["链球菌感染", "葡萄球菌感染", "皮肤破损", "溃疡", "足癣", "免疫力低下"],
    "treatment": ["静脉抗生素治疗", "口服抗生素", "外科引流", "休息抬高患肢", "治疗原发病"],
    "precautions": ["保持皮肤完整", "及时治疗伤口", "控制糖尿病", "治疗足癣", "避免外伤"],
    "severity": "moderate_to_severe",
    "department": "皮肤科/外科",
    "common_population": ["糖尿病患者", "静脉功能不全者", "免疫力低下者", "老年人"],
    "related_diseases": ["丹毒", "脓肿", "坏死性筋膜炎", "糖尿病足"]
  },
  {
    "disease_name": "体癣",
    "aliases": ["圆癣", "金钱癣", "tinea corporis"],
    "overview": "体癣是由皮肤癣菌感染引起的浅表真菌病，好发于面部、躯干和四肢，表现为环形或多环形皮损。",
    "symptoms": ["环形红斑", "边缘隆起", "鳞屑", "中心消退", "瘙痒", "逐渐扩大"],
    "causes": ["红色毛癣菌", "须癣毛癣菌", "犬小孢子菌", "接触传染", "免疫力低下", "湿热环境"],
    "treatment": ["外用抗真菌药（特比萘芬）", "口服抗真菌药（伊曲康唑）", "保持干燥", "消毒衣物"],
    "precautions": ["保持皮肤干燥", "避免接触患病动物", "不共用衣物毛巾", "勤换内衣", "治疗足癣"],
    "severity": "mild",
    "department": "皮肤科",
    "common_population": ["各年龄段", "养宠物者", "运动员", "湿热地区居民"],
    "related_diseases": ["股癣", "足癣", "手癣", "甲癣"]
  },
  {
    "disease_name": "股癣",
    "aliases": ["阴股癣", "tinea cruris"],
    "overview": "股癣是发生于腹股沟、会阴、肛周和臀部的皮肤癣菌感染，多见于男性，与局部潮湿多汗有关。",
    "symptoms": ["腹股沟红斑", "鳞屑", "边界清楚", "瘙痒明显", "可扩展至臀部", "反复发作"],
    "causes": ["红色毛癣菌", "絮状表皮癣菌", "局部潮湿多汗", "肥胖", "糖尿病", "长期坐位"],
    "treatment": ["外用抗真菌药", "口服抗真菌药", "保持干燥", "穿宽松内衣", "治疗足癣"],
    "precautions": ["保持局部干燥", "穿透气内衣", "避免久坐", "控制体重", "不共用毛巾"],
    "severity": "mild",
    "department": "皮肤科",
    "common_population": ["青年男性", "肥胖者", "糖尿病患者", "运动员"],
    "related_diseases": ["足癣", "体癣", "念珠菌性间擦疹"]
  },
  {
    "disease_name": "足癣",
    "aliases": ["脚气", "香港脚", "tinea pedis"],
    "overview": "足癣是由皮肤癣菌感染足部引起的浅表真菌病，是最常见的皮肤真菌感染，表现为水疱、脱屑或糜烂。",
    "symptoms": ["趾间糜烂", "水疱", "脱屑", "瘙痒", "异味", "角化过度"],
    "causes": ["红色毛癣菌", "须癣毛癣菌", "絮状表皮癣菌", "足部多汗", "穿不透气的鞋", "公共场所赤足"],
    "treatment": ["外用抗真菌药", "口服抗真菌药（严重病例）", "保持干燥", "消毒鞋袜", "联合用药"],
    "precautions": ["保持足部干燥", "穿透气鞋袜", "勤换鞋袜", "公共场所穿拖鞋", "不共用拖鞋毛巾", "治疗甲癣"],
    "severity": "mild",
    "department": "皮肤科",
    "common_population": ["各年龄段", "男性多于女性", "运动员", "湿热地区居民"],
    "related_diseases": ["甲癣", "股癣", "体癣", "丹毒"]
  },
  {
    "disease_name": "手癣",
    "aliases": ["鹅掌风", "tinea manuum"],
    "overview": "手癣是皮肤癣菌感染手部引起的浅表真菌病，多为单侧发病，常由足癣自身传染而来。",
    "symptoms": ["手掌红斑", "脱屑", "角化过度", "水疱", "瘙痒", "皲裂"],
    "causes": ["红色毛癣菌", "须癣毛癣菌", "自体接种（足癣）", "接触传染", "手部潮湿"],
    "treatment": ["外用抗真菌药", "口服抗真菌药", "角质剥脱剂", "保湿剂", "治疗足癣"],
    "precautions": ["保持手部干燥", "避免搔抓足部", "治疗足癣", "避免接触刺激物", "戴手套防护"],
    "severity": "mild",
    "department": "皮肤科",
    "common_population": ["成年人", "足癣患者", "手部经常接触水者", "家庭主妇"],
    "related_diseases": ["足癣", "甲癣", "湿疹", "汗疱疹"]
  },
  {
    "disease_name": "甲癣",
    "aliases": ["灰指甲", "onychomycosis", "tinea unguium"],
    "overview": "甲癣是由皮肤癣菌、酵母菌或霉菌感染甲板或甲床引起的疾病，是最常见的甲病，表现为甲板变色、增厚、变形。",
    "symptoms": ["甲板变色（黄、白、褐）", "甲板增厚", "甲板变形", "甲下碎屑", "甲板与甲床分离"],
    "causes": ["红色毛癣菌", "须癣毛癣菌", "念珠菌", "霉菌", "足癣蔓延", "免疫力低下", "外伤"],
    "treatment": ["口服抗真菌药（特比萘芬、伊曲康唑）", "外用抗真菌药", "激光治疗", "手术拔甲", "联合治疗"],
    "precautions": ["保持手足干燥", "治疗足癣", "避免甲外伤", "不共用指甲剪", "穿透气鞋袜", "坚持治疗"],
    "severity": "mild",
    "department": "皮肤科",
    "common_population": ["成年人", "足癣患者", "老年人", "糖尿病患者", "免疫力低下者"],
    "related_diseases": ["足癣", "手癣", "银屑病甲", "扁平苔藓"]
  },
  {
    "disease_name": "花斑癣",
    "aliases": ["汗斑", "tinea versicolor", "pityriasis versicolor"],
    "overview": "花斑癣是由马拉色菌感染引起的浅表真菌病，好发于胸背部，表现为色素减退或加深的斑片，表面有细屑。",
    "symptoms": ["圆形或椭圆形斑片", "色素减退或加深", "表面细屑", "轻度瘙痒", "夏季加重", "冬季减轻"],
    "causes": ["马拉色菌感染", "多汗", "油脂分泌旺盛", "高温高湿环境", "免疫力低下", "遗传因素"],
    "treatment": ["外用抗真菌药（酮康唑洗剂）", "外用二硫化硒", "口服抗真菌药（严重病例）", "保持干燥"],
    "precautions": ["勤洗澡更衣", "保持皮肤干燥", "穿透气衣物", "避免过度出汗", "消毒衣物", "预防复发"],
    "severity": "mild",
    "department": "皮肤科",
    "common_population": ["青壮年男性", "多汗者", "热带地区居民", "免疫力低下者"],
    "related_diseases": ["白癜风", "玫瑰糠疹", "脂溢性皮炎"]
  },
  {
    "disease_name": "皮肤念珠菌病",
    "aliases": ["cutaneous candidiasis", "念珠菌感染"],
    "overview": "皮肤念珠菌病是由念珠菌属真菌感染引起的皮肤病，好发于皮肤皱褶部位，表现为红斑、糜烂和卫星状丘疹。",
    "symptoms": ["红斑", "糜烂", "卫星状丘疹或脓疱", "白色伪膜", "瘙痒或疼痛", "边界清楚"],
    "causes": ["白色念珠菌", "局部潮湿", "免疫力低下", "糖尿病", "长期使用抗生素或激素", "肥胖"],
    "treatment": ["外用抗真菌药（制霉菌素、咪康唑）", "口服抗真菌药", "保持干燥", "治疗原发病", "控制血糖"],
    "precautions": ["保持皮肤皱褶部位干燥", "控制血糖", "避免长期使用抗生素", "穿透气衣物", "控制体重"],
    "severity": "mild",
    "department": "皮肤科",
    "common_population": ["婴儿（尿布区）", "糖尿病患者", "肥胖者", "免疫力低下者", "老年人"],
    "related_diseases": ["间擦疹", "股癣", "口腔念珠菌病", "阴道炎"]
  },
  {
    "disease_name": "疥疮",
    "aliases": ["scabies", "疥螨病"],
    "overview": "疥疮是由疥螨寄生皮肤引起的传染性皮肤病，表现为剧烈瘙痒的丘疹、水疱和隧道，夜间瘙痒加重。",
    "symptoms": ["剧烈瘙痒（夜间加重）", "丘疹", "水疱", "隧道（指缝、腕部）", "结节（阴囊）", "抓痕"],
    "causes": ["人型疥螨寄生", "密切接触传播", "性接触传播", "共用衣物被褥", "卫生条件差"],
    "treatment": ["外用硫磺软膏", "外用扑灭司林", "口服伊维菌素", "全家同治", "消毒衣物被褥"],
    "precautions": ["避免密切接触", "勤洗澡更衣", "消毒衣物被褥", "全家同时治疗", "避免搔抓"],
    "severity": "moderate",
    "department": "皮肤科",
    "common_population": ["集体生活者", "卫生条件差者", "性活跃人群", "免疫力低下者"],
    "related_diseases": ["湿疹", "痒疹", "虱病"]
  },
  {
    "disease_name": "湿疹",
    "aliases": ["湿疮", "eczema", "特应性皮炎"],
    "overview": "湿疹是由多种内外因素引起的一种具有明显渗出倾向的皮肤炎症反应，急性期皮疹呈多样性，慢性期表现为局限性肥厚性斑块，瘙痒剧烈，易复发。",
    "symptoms": ["瘙痒", "红斑", "丘疹", "水疱", "渗出", "结痂", "苔藓样变", "皮肤干燥"],
    "causes": ["免疫系统异常", "遗传因素", "过敏体质", "环境刺激（尘螨、花粉）", "精神压力", "感染因素"],
    "treatment": ["外用糖皮质激素", "保湿剂", "抗组胺药", "免疫抑制剂", "中药治疗", "光疗"],
    "precautions": ["避免抓挠患处", "保持皮肤湿润", "避免接触过敏源", "注意饮食清淡", "避免过度清洁"],
    "severity": "chronic",
    "department": "皮肤科",
    "common_population": ["儿童", "过敏体质人群", "有家族过敏史者", "精神压力大者"],
    "related_diseases": ["哮喘", "过敏性鼻炎", "特应性皮炎"]
  },
  {
    "disease_name": "特应性皮炎",
    "aliases": ["异位性皮炎", "atopic dermatitis", "遗传过敏性皮炎"],
    "overview": "特应性皮炎是一种与遗传过敏体质有关的慢性、复发性、炎症性皮肤病，患者常有家族过敏史，临床表现为皮肤干燥、剧烈瘙痒和湿疹样皮疹。",
    "symptoms": ["皮肤干燥", "剧烈瘙痒", "湿疹样皮疹", "苔藓样变", "干皮症", "掌纹症", "眶周黑晕"],
    "causes": ["遗传因素", "免疫异常", "皮肤屏障功能障碍", "环境因素", "微生物定植", "精神因素"],
    "treatment": ["外用糖皮质激素", "外用钙调神经磷酸酶抑制剂", "抗组胺药", "免疫抑制剂", "生物制剂", "光疗"],
    "precautions": ["保持皮肤湿润", "避免接触过敏原", "避免搔抓", "穿着纯棉衣物", "避免过度清洁", "控制环境温湿度"],
    "severity": "chronic",
    "department": "皮肤科",
    "common_population": ["婴幼儿（1岁前发病者约60%）", "有家族过敏史者", "城市居民", "发达国家人群"],
    "related_diseases": ["哮喘", "过敏性鼻炎", "过敏性结膜炎", "食物过敏"]
  },
  {
    "disease_name": "接触性皮炎",
    "aliases": ["contact dermatitis", "过敏性接触性皮炎"],
    "overview": "接触性皮炎是由于皮肤接触到某些外源性物质后，在接触部位甚至以外的部位发生的炎症性反应，可分为刺激性和过敏性两种类型。",
    "symptoms": ["红斑", "丘疹", "水疱", "渗出", "瘙痒", "疼痛", "边界清楚"],
    "causes": ["刺激性物质（强酸、强碱）", "过敏性物质（金属、化妆品、植物）", "接触史", "过敏体质", "职业暴露"],
    "treatment": ["避免接触过敏原", "外用糖皮质激素", "口服抗组胺药", "湿敷", "口服糖皮质激素（严重病例）"],
    "precautions": ["避免接触已知过敏原", "戴手套防护", "使用防护霜", "做斑贴试验", "更换化妆品品牌"],
    "severity": "acute",
    "department": "皮肤科",
    "common_population": ["过敏体质者", "从事接触刺激性物质的职业者", "女性（化妆品接触）", "儿童"],
    "related_diseases": ["湿疹", "荨麻疹", "药疹"]
  },
  {
    "disease_name": "脂溢性皮炎",
    "aliases": ["seborrheic dermatitis", "脂溢性湿疹"],
    "overview": "脂溢性皮炎是常见于头、面、胸背部或会阴部等皮脂溢出部位的慢性、复发性、炎症性皮肤病，与马拉色菌感染和皮脂分泌旺盛有关。",
    "symptoms": ["油腻性鳞屑", "黄红色斑片", "瘙痒", "头皮屑增多", "脱发", "面部油腻"],
    "causes": ["马拉色菌感染", "皮脂分泌旺盛", "遗传因素", "精神因素", "饮食因素", "B族维生素缺乏"],
    "treatment": ["外用抗真菌药（酮康唑）", "外用糖皮质激素", "二硫化硒洗剂", "口服抗真菌药", "维生素B族补充"],
    "precautions": ["保持皮肤清洁", "避免过度清洁", "饮食清淡", "规律作息", "避免精神紧张", "使用温和的洗护用品"],
    "severity": "mild_to_moderate",
    "department": "皮肤科",
    "common_population": ["婴儿（3-4周）", "青少年", "成年人", "油性皮肤者", "帕金森病患者"],
    "related_diseases": ["痤疮", "酒渣鼻", "银屑病", "特应性皮炎"]
  },
  {
    "disease_name": "神经性皮炎",
    "aliases": ["慢性单纯性苔藓", "lichen simplex chronicus", "牛皮癣"],
    "overview": "神经性皮炎是以阵发性剧痒和皮肤苔藓样变为特征的慢性炎症性皮肤病，与精神因素、搔抓、摩擦等有关。",
    "symptoms": ["剧烈瘙痒（阵发性）", "皮肤苔藓样变", "皮肤增厚", "纹理加深", "多角形丘疹", "抓痕"],
    "causes": ["精神因素（焦虑、紧张）", "搔抓摩擦", "局部刺激", "内分泌失调", "胃肠道功能障碍"],
    "treatment": ["外用糖皮质激素", "止痒药物", "抗组胺药", "心理治疗", "光疗", "避免搔抓"],
    "precautions": ["避免搔抓", "保持情绪稳定", "避免局部刺激", "穿着宽松衣物", "规律作息", "避免辛辣食物"],
    "severity": "chronic",
    "department": "皮肤科",
    "common_population": ["青年或中年", "精神压力大者", "失眠者", "焦虑症患者"],
    "related_diseases": ["湿疹", "瘙痒症", "焦虑症"]
  },
  {
    "disease_name": "虫咬皮炎",
    "aliases": ["丘疹性荨麻疹", "insect bite dermatitis", "虫咬性皮炎"],
    "overview": "虫咬皮炎是由昆虫叮咬或毒汁刺激引起的皮肤炎症反应，表现为散在的红色丘疹，顶端常有水疱，伴有剧烈瘙痒。",
    "symptoms": ["红色丘疹", "水疱", "瘙痒", "红肿", "疼痛", "风团"],
    "causes": ["蚊子叮咬", "螨虫叮咬", "跳蚤叮咬", "臭虫叮咬", "蜜蜂蜇伤", "环境潮湿"],
    "treatment": ["外用止痒药物", "糖皮质激素软膏", "口服抗组胺药", "冷敷", "避免搔抓", "预防感染"],
    "precautions": ["使用蚊帐", "喷洒驱虫剂", "穿着长袖衣物", "保持环境清洁", "避免去草丛", "宠物除虫"],
    "severity": "mild",
    "department": "皮肤科",
    "common_population": ["儿童", "户外活动者", "居住环境潮湿者", "宠物饲养者"],
    "related_diseases": ["荨麻疹", "湿疹", "皮肤感染"]
  },
  {
    "disease_name": "日光性皮炎",
    "aliases": ["日晒伤", "sunburn", "紫外线皮炎"],
    "overview": "日光性皮炎是由于皮肤过度暴露于紫外线辐射后引起的急性炎症反应，表现为暴露部位的红斑、水肿，严重时可出现水疱。",
    "symptoms": ["红斑", "水肿", "水疱", "灼痛", "瘙痒", "脱皮", "色素沉着"],
    "causes": ["紫外线过度照射", "皮肤对紫外线敏感", "长期暴露", "高原地区", "夏季阳光强烈", "服用光敏药物"],
    "treatment": ["冷敷", "外用糖皮质激素", "口服抗组胺药", "止痛药", "保湿剂", "避免再次日晒"],
    "precautions": ["涂抹防晒霜", "穿着防晒衣物", "避免中午日晒", "使用遮阳伞", "戴宽檐帽", "避免光敏药物"],
    "severity": "mild_to_moderate",
    "department": "皮肤科",
    "common_population": ["皮肤白皙者", "长期户外活动者", "高原居民", "服用光敏药物者"],
    "related_diseases": ["多形性日光疹", "慢性光化性皮炎", "光线性角化病"]
  },
  {
    "disease_name": "淤积性皮炎",
    "aliases": ["下肢淤积性皮炎", "stasis dermatitis", "静脉曲张性皮炎"],
    "overview": "淤积性皮炎多发生于下肢，与下肢静脉血液回流不畅、淤血有关，常见于长期站立或患有下肢静脉曲张的人群。",
    "symptoms": ["下肢皮肤水肿", "红斑", "瘙痒", "色素沉着", "苔藓样变", "溃疡"],
    "causes": ["下肢静脉曲张", "静脉瓣膜功能不全", "长期站立", "肥胖", "妊娠", "静脉血栓"],
    "treatment": ["抬高患肢", "弹力绷带", "外用糖皮质激素", "口服抗组胺药", "改善循环药物", "手术治疗"],
    "precautions": ["避免长时间站立", "穿弹力袜", "抬高下肢", "控制体重", "治疗静脉曲张", "避免搔抓"],
    "severity": "chronic",
    "department": "皮肤科/血管外科",
    "common_population": ["中老年人", "长期站立工作者", "静脉曲张患者", "肥胖者"],
    "related_diseases": ["下肢静脉曲张", "静脉溃疡", "血栓性静脉炎"]
  },
  {
    "disease_name": "自身敏感性皮炎",
    "aliases": ["autoeczematization", "自身湿疹化"],
    "overview": "自身敏感性皮炎常因皮肤局部存在原发的湿疹、皮炎等病灶，由于处理不当，导致局部炎症加重，引起全身泛发性皮疹。",
    "symptoms": ["原发病灶加重", "全身泛发性红斑", "丘疹", "水疱", "瘙痒", "发热"],
    "causes": ["原发湿疹或皮炎", "过度搔抓", "外用刺激性药物", "感染", "过敏反应", "免疫力低下"],
    "treatment": ["治疗原发病灶", "系统使用糖皮质激素", "抗组胺药", "抗生素（继发感染）", "外用药物", "避免刺激"],
    "precautions": ["及时治疗原发皮损", "避免搔抓", "避免使用刺激性药物", "保持皮肤清洁", "增强免疫力", "避免感染"],
    "severity": "moderate",
    "department": "皮肤科",
    "common_population": ["湿疹患者", "皮炎患者", "免疫力低下者", "皮肤屏障受损者"],
    "related_diseases": ["湿疹", "接触性皮炎", "药疹"]
  },
  {
    "disease_name": "夏季皮炎",
    "aliases": ["summer dermatitis", "夏令皮炎"],
    "overview": "夏季皮炎是由于夏季高温、潮湿环境引起的一种季节性炎症性皮肤病，好发于四肢伸侧，表现为红斑、丘疹，伴有剧烈瘙痒。",
    "symptoms": ["红斑", "丘疹", "瘙痒", "抓痕", "血痂", "皮肤粗糙"],
    "causes": ["高温", "潮湿", "出汗", "紫外线照射", "局部摩擦", "汗液刺激"],
    "treatment": ["保持凉爽", "外用糖皮质激素", "抗组胺药", "炉甘石洗剂", "避免搔抓", "保持皮肤清洁"],
    "precautions": ["保持室内通风", "穿着宽松透气衣物", "避免搔抓", "勤洗澡", "使用痱子粉", "避免高温环境"],
    "severity": "mild",
    "department": "皮肤科",
    "common_population": ["高温环境工作者", "肥胖者", "出汗较多者", "儿童"],
    "related_diseases": ["痱子", "湿疹", "日光性皮炎"]
  },
  {
    "disease_name": "激素依赖性皮炎",
    "aliases": ["糖皮质激素依赖性皮炎", "steroid依赖性皮炎"],
    "overview": "激素依赖性皮炎是由于长期外用糖皮质激素制剂后，皮肤对激素产生依赖性，停药后出现反跳现象的一种皮肤病。",
    "symptoms": ["皮肤变薄", "毛细血管扩张", "痤疮样皮疹", "色素沉着", "干燥脱屑", "灼热瘙痒"],
    "causes": ["长期外用糖皮质激素", "滥用激素化妆品", "不正确使用激素", "使用强效激素", "面部皮肤敏感"],
    "treatment": ["逐渐减少激素使用", "替代治疗（钙调神经磷酸酶抑制剂）", "保湿修复", "抗组胺药", "光疗", "心理治疗"],
    "precautions": ["避免滥用激素", "选择弱效激素", "短期使用", "使用保湿剂", "避免刺激", "规律作息"],
    "severity": "chronic",
    "department": "皮肤科",
    "common_population": ["面部皮肤病患者", "滥用化妆品者", "长期使用激素者", "皮肤敏感者"],
    "related_diseases": ["痤疮", "玫瑰痤疮", "接触性皮炎"]
  },
  {
    "disease_name": "银屑病",
    "aliases": ["牛皮癣", "psoriasis", "干癣"],
    "overview": "银屑病是一种遗传与环境共同作用诱发的免疫介导的慢性、复发性、炎症性、系统性疾病，典型临床表现为鳞屑性红斑或斑块，局限或广泛分布，无传染性。",
    "symptoms": ["鳞屑性红斑或斑块", "银白色鳞屑", "蜡滴现象", "薄膜现象", "点状出血（Auspitz征）", "瘙痒", "束状发（头皮）", "顶针状甲凹陷"],
    "causes": ["遗传因素（约30%有家族史）", "免疫系统异常（T淋巴细胞介导）", "环境因素（感染、创伤）", "精神压力", "某些药物（β受体阻滞剂、锂剂等）", "吸烟、酗酒", "肥胖"],
    "treatment": ["外用维生素D3衍生物（卡泊三醇）", "外用糖皮质激素", "维A酸类药物", "光疗（窄波紫外线）", "免疫抑制剂（甲氨蝶呤、环孢素）", "生物制剂（TNF-α抑制剂、IL-17抑制剂）"],
    "precautions": ["避免搔抓和外伤（防止同形反应）", "保持皮肤湿润", "预防上呼吸道感染", "戒烟限酒", "避免使用刺激性药物", "生活规律，劳逸结合"],
    "severity": "chronic",
    "department": "皮肤科",
    "common_population": ["各年龄段均可发病", "约2/3患者在40岁前发病", "有家族史者", "北方人群多于南方"],
    "related_diseases": ["银屑病关节炎", "代谢综合征", "心血管疾病", "糖尿病"]
  },
  {
    "disease_name": "玫瑰糠疹",
    "aliases": ["pityriasis rosea", "梅花糠疹"],
    "overview": "玫瑰糠疹是一种常见的自限性炎症性皮肤病，好发于躯干和四肢近端，表现为覆有糠状鳞屑的玫瑰色斑疹、斑丘疹，病程有自限性，一般6-8周可自愈。",
    "symptoms": ["前驱斑（母斑）", "玫瑰色斑疹", "糠状鳞屑", "椭圆形皮损", "长轴与皮纹一致", "轻度瘙痒"],
    "causes": ["病毒感染（可能与疱疹病毒6、7型有关）", "免疫反应", "药物因素", "季节性因素（春秋季多发）", "感染因素"],
    "treatment": ["抗组胺药", "外用糖皮质激素", "光疗（窄波UVB）", "炉甘石洗剂", "维生素C", "对症治疗"],
    "precautions": ["避免热水烫洗", "避免搔抓", "保持皮肤清洁", "避免刺激性食物", "注意休息", "预防感染"],
    "severity": "mild",
    "department": "皮肤科",
    "common_population": ["青少年和青年（10-35岁）", "春秋季节", "女性略多于男性", "免疫力正常者"],
    "related_diseases": ["银屑病", "花斑癣", "二期梅毒疹", "药疹"]
  },
  {
    "disease_name": "扁平苔藓",
    "aliases": ["lichen planus", "扁平红苔藓"],
    "overview": "扁平苔藓是一种特发性炎症性皮肤病，表现为多角形扁平紫红色丘疹，可融合成鳞屑性斑块，黏膜常受累，病程慢性。",
    "symptoms": ["多角形扁平丘疹", "紫红色", "蜡样光泽", "Wickham纹", "瘙痒", "黏膜损害（口腔、生殖器）", "指甲损害"],
    "causes": ["免疫因素", "遗传因素", "病毒感染", "药物因素", "精神因素", "自身免疫"],
    "treatment": ["外用糖皮质激素", "维A酸类药物", "免疫抑制剂", "光疗", "抗组胺药", "对症治疗"],
    "precautions": ["避免搔抓", "避免刺激性食物", "保持口腔卫生", "避免使用刺激性药物", "保持情绪稳定", "定期随访"],
    "severity": "chronic",
    "department": "皮肤科",
    "common_population": ["中年人（30-60岁）", "女性略多于男性", "免疫功能异常者", "有家族史者"],
    "related_diseases": ["口腔扁平苔藓", "甲扁平苔藓", "银屑病", "慢性湿疹"]
  },
  {
    "disease_name": "红皮病",
    "aliases": ["剥脱性皮炎", "erythroderma", "exfoliative dermatitis"],
    "overview": "红皮病是一种严重的炎症性皮肤病，表现为全身皮肤弥漫性潮红、肿胀、脱屑，可伴有发热等全身症状，常由其他皮肤病发展而来。",
    "symptoms": ["全身皮肤潮红", "肿胀", "大量脱屑", "发热", "淋巴结肿大", "指甲改变", "毛发脱落"],
    "causes": ["银屑病恶化", "药物过敏", "特应性皮炎", "淋巴瘤", "皮肤T细胞淋巴瘤", "其他皮肤病"],
    "treatment": ["系统使用糖皮质激素", "免疫抑制剂", "支持治疗", "对症治疗", "治疗原发病", "预防感染"],
    "precautions": ["保持皮肤清洁", "避免刺激", "加强营养", "预防感染", "密切监测", "心理支持"],
    "severity": "severe",
    "department": "皮肤科",
    "common_population": ["银屑病患者", "药物过敏者", "淋巴瘤患者", "老年人"],
    "related_diseases": ["银屑病", "药物性皮炎", "淋巴瘤", "特应性皮炎"]
  },
  {
    "disease_name": "毛发红糠疹",
    "aliases": ["pityriasis rubra pilaris", "毛发糠疹"],
    "overview": "毛发红糠疹是一种慢性炎症性皮肤病，表现为毛囊角化性丘疹和糠秕状鳞屑，好发于四肢伸侧，可发展为红皮病。",
    "symptoms": ["毛囊角化性丘疹", "糠秕状鳞屑", "红色斑块", "掌跖角化", "头皮鳞屑", "瘙痒"],
    "causes": ["遗传因素", "维生素A缺乏", "角化障碍", "免疫因素", "感染因素", "药物因素"],
    "treatment": ["维生素A", "维A酸类药物", "外用角质剥脱剂", "糖皮质激素", "免疫抑制剂", "光疗"],
    "precautions": ["避免搔抓", "保持皮肤湿润", "避免刺激性食物", "补充维生素A", "定期随访", "避免感染"],
    "severity": "chronic",
    "department": "皮肤科",
    "common_population": ["儿童和青少年", "有家族史者", "维生素A缺乏者", "免疫力低下者"],
    "related_diseases": ["银屑病", "鱼鳞病", "毛周角化病", "掌跖角化病"]
  },
  {
    "disease_name": "多形红斑",
    "aliases": ["erythema multiforme", "多形渗出性红斑"],
    "overview": "多形红斑是一种以靶形或虹膜状红斑为特征的急性炎症性皮肤病，常与感染、药物等因素有关，可累及黏膜。",
    "symptoms": ["靶形红斑", "虹膜状损害", "水疱", "黏膜损害", "瘙痒或疼痛", "发热", "关节痛"],
    "causes": ["单纯疱疹病毒感染", "药物过敏", "支原体感染", "细菌感染", "自身免疫", "恶性肿瘤"],
    "treatment": ["治疗原发病", "抗组胺药", "糖皮质激素", "抗病毒药物", "支持治疗", "预防感染"],
    "precautions": ["避免可疑药物", "治疗感染", "保持皮肤清洁", "避免搔抓", "注意休息", "加强营养"],
    "severity": "mild_to_severe",
    "department": "皮肤科",
    "common_population": ["青年", "单纯疱疹病毒感染者", "药物过敏者", "春秋季节"],
    "related_diseases": [" Stevens-Johnson综合征", "中毒性表皮坏死松解症", "单纯疱疹", "药疹"]
  },
  {
    "disease_name": "副银屑病",
    "aliases": ["parapsoriasis", "类银屑病"],
    "overview": "副银屑病是一组病因不明的慢性皮肤病，临床表现为红斑、丘疹、鳞屑，与银屑病相似但症状较轻，病程慢性。",
    "symptoms": ["红斑", "丘疹", "鳞屑", "轻度瘙痒", "好发于躯干", "慢性病程"],
    "causes": ["病因不明", "免疫因素", "感染因素", "环境因素", "遗传因素"],
    "treatment": ["外用糖皮质激素", "光疗", "维A酸类药物", "免疫调节剂", "对症治疗", "定期随访"],
    "precautions": ["避免搔抓", "保持皮肤清洁", "避免刺激", "定期检查", "注意观察病情变化", "避免感染"],
    "severity": "chronic",
    "department": "皮肤科",
    "common_population": ["中年人", "男性略多于女性", "免疫力低下者", "有家族史者"],
    "related_diseases": ["银屑病", "蕈样肉芽肿", "玫瑰糠疹", "扁平苔藓"]
  },
  {
    "disease_name": "单纯糠疹",
    "aliases": ["白色糠疹", "pityriasis alba", "桃花癣"],
    "overview": "单纯糠疹是一种好发于儿童面部的轻度炎症性皮肤病，表现为圆形或椭圆形淡白色斑，表面有细小鳞屑。",
    "symptoms": ["淡白色斑", "表面鳞屑", "圆形或椭圆形", "好发于面部", "轻度瘙痒", "无自觉症状"],
    "causes": ["马拉色菌感染", "维生素缺乏", "日晒", "皮肤干燥", "寄生虫感染", "营养不良"],
    "treatment": ["保湿剂", "外用酮康唑", "维生素B族", "避免日晒", "对症治疗", "无需特殊治疗"],
    "precautions": ["保持皮肤清洁", "避免过度清洗", "防晒", "补充维生素", "均衡饮食", "使用温和的护肤品"],
    "severity": "mild",
    "department": "皮肤科",
    "common_population": ["儿童", "青少年", "春季多发", "皮肤干燥者"],
    "related_diseases": ["白癜风", "花斑癣", "贫血痣", "无色素痣"]
  },
  {
    "disease_name": "光泽苔藓",
    "aliases": ["lichen nitidus", "光泽扁平苔藓"],
    "overview": "光泽苔藓是一种原因不明的慢性炎症性皮肤病，表现为群集性的微小发亮的丘疹，好发于阴茎、腹部、前臂等部位。",
    "symptoms": ["微小发亮丘疹", "肤色或淡红色", "群集分布", "无自觉症状", "好发于生殖器", "慢性病程"],
    "causes": ["病因不明", "免疫因素", "遗传因素", "感染因素", "精神因素"],
    "treatment": ["无需治疗", "外用糖皮质激素", "维A酸类药物", "光疗", "对症治疗", "观察随访"],
    "precautions": ["避免搔抓", "保持皮肤清洁", "避免刺激", "定期随访", "注意观察病情变化", "保持情绪稳定"],
    "severity": "mild",
    "department": "皮肤科",
    "common_population": ["儿童和青少年", "男性多于女性", "免疫力正常者", "无特定人群"],
    "related_diseases": ["扁平苔藓", "传染性软疣", "毛周角化病", "小棘苔藓"]
  },
  {
    "disease_name": "硬化性苔藓",
    "aliases": ["lichen sclerosus", "硬萎"],
    "overview": "硬化性苔藓是一种慢性炎症性皮肤病，主要累及外生殖器和肛门周围，表现为白色萎缩性斑块，可导致皮肤萎缩和粘连。",
    "symptoms": ["白色萎缩性斑块", "皮肤变薄", "瘙痒", "疼痛", "皲裂", "粘连", "色素减退"],
    "causes": ["免疫因素", "遗传因素", "激素水平变化", "感染因素", "外伤", "自身免疫"],
    "treatment": ["外用糖皮质激素", "钙调神经磷酸酶抑制剂", "维A酸类药物", "光疗", "手术治疗", "对症治疗"],
    "precautions": ["保持局部清洁", "避免搔抓", "避免刺激", "定期随访", "注意观察病情变化", "避免外伤"],
    "severity": "chronic",
    "department": "皮肤科/妇科",
    "common_population": ["女性（绝经期前后）", "男性（包皮过长者）", "儿童", "有家族史者"],
    "related_diseases": ["扁平苔藓", "生殖器白斑", "外阴癌前病变", "白癜风"]
  },
  {
    "disease_name": "系统性红斑狼疮",
    "aliases": ["systemic lupus erythematosus", "SLE", "红斑狼疮"],
    "overview": "系统性红斑狼疮是一种自身免疫性疾病，可累及全身多个系统和器官，皮肤表现为面部蝶形红斑，还可出现发热、关节痛等全身症状。",
    "symptoms": ["面部蝶形红斑", "盘状红斑", "光敏感", "口腔溃疡", "脱发", "关节痛", "发热", "肾脏损害"],
    "causes": ["遗传因素", "环境因素（紫外线、感染）", "雌激素水平", "免疫异常", "药物因素", "病毒感染"],
    "treatment": ["糖皮质激素", "免疫抑制剂", "抗疟药（羟氯喹）", "生物制剂", "对症治疗", "支持治疗"],
    "precautions": ["避免日晒", "避免感染", "避免使用诱发药物", "定期随访", "保持情绪稳定", "避免劳累"],
    "severity": "severe",
    "department": "风湿免疫科/皮肤科",
    "common_population": ["年轻女性（15-40岁）", "有家族史者", "亚裔人群", "女性多于男性（9:1）"],
    "related_diseases": ["盘状红斑狼疮", "亚急性皮肤型红斑狼疮", "干燥综合征", "类风湿关节炎"]
  },
  {
    "disease_name": "盘状红斑狼疮",
    "aliases": ["discoid lupus erythematosus", "DLE", "慢性皮肤型红斑狼疮"],
    "overview": "盘状红斑狼疮是红斑狼疮的一种类型，主要累及皮肤，表现为境界清楚的盘状红斑，表面有鳞屑，好发于面部、头皮等部位。",
    "symptoms": ["盘状红斑", "鳞屑", "毛囊角栓", "色素沉着或减退", "瘢痕形成", "脱发", "轻度瘙痒"],
    "causes": ["遗传因素", "紫外线照射", "免疫异常", "环境因素", "激素水平", "感染因素"],
    "treatment": ["外用糖皮质激素", "抗疟药（羟氯喹）", "维A酸类药物", "免疫抑制剂", "避免日晒", "对症治疗"],
    "precautions": ["避免日晒", "避免搔抓", "保持皮肤清洁", "定期随访", "注意观察病情变化", "避免感染"],
    "severity": "chronic",
    "department": "皮肤科",
    "common_population": ["中年人", "女性多于男性", "有家族史者", "紫外线敏感者"],
    "related_diseases": ["系统性红斑狼疮", "亚急性皮肤型红斑狼疮", "皮肌炎", "硬皮病"]
  },
  {
    "disease_name": "皮肌炎",
    "aliases": ["dermatomyositis", "DM", "皮肤肌肉炎"],
    "overview": "皮肌炎是一种主要累及皮肤和肌肉的自身免疫性疾病，表现为眼睑紫红色斑、Gottron丘疹，伴有肌肉无力、疼痛等症状。",
    "symptoms": ["眼睑紫红色斑", "Gottron丘疹", "皮肤异色症", "肌肉无力", "肌肉疼痛", "发热", "关节痛"],
    "causes": ["自身免疫异常", "遗传因素", "感染因素", "肿瘤相关性", "环境因素", "药物因素"],
    "treatment": ["糖皮质激素", "免疫抑制剂", "生物制剂", "支持治疗", "物理治疗", "治疗原发病"],
    "precautions": ["避免日晒", "避免感染", "注意休息", "定期随访", "监测肌肉功能", "筛查肿瘤"],
    "severity": "severe",
    "department": "风湿免疫科/皮肤科",
    "common_population": ["儿童和成人", "女性多于男性", "40-60岁", "肿瘤患者"],
    "related_diseases": ["多发性肌炎", "系统性红斑狼疮", "硬皮病", "干燥综合征"]
  },
  {
    "disease_name": "硬皮病",
    "aliases": ["scleroderma", "系统性硬化症", "硬肿病"],
    "overview": "硬皮病是一种以皮肤纤维化和内脏器官纤维化为特征的自身免疫性疾病，分为局限性和系统性两种类型。",
    "symptoms": ["皮肤硬化", "雷诺现象", "面部表情减少", "关节僵硬", "吞咽困难", "肺纤维化", "肾功能损害"],
    "causes": ["自身免疫异常", "遗传因素", "环境因素", "感染因素", "微嵌合现象", "血管异常"],
    "treatment": ["糖皮质激素", "免疫抑制剂", "血管扩张剂", "抗纤维化药物", "对症治疗", "支持治疗"],
    "precautions": ["避免寒冷刺激", "戒烟", "避免感染", "注意保暖", "定期随访", "监测内脏功能"],
    "severity": "severe",
    "department": "风湿免疫科/皮肤科",
    "common_population": ["30-50岁", "女性多于男性（3:1）", "有家族史者", "环境暴露者"],
    "related_diseases": ["系统性红斑狼疮", "皮肌炎", "干燥综合征", "混合性结缔组织病"]
  },
  {
    "disease_name": "干燥综合征",
    "aliases": ["Sjögren's syndrome", "SS", "舍格伦综合征"],
    "overview": "干燥综合征是一种主要累及外分泌腺体的慢性炎症性自身免疫病，表现为口干、眼干，还可累及其他系统。",
    "symptoms": ["口干", "眼干", "猖獗性龋齿", "腮腺肿大", "关节痛", "皮肤干燥", "乏力", "雷诺现象"],
    "causes": ["自身免疫异常", "遗传因素", "感染因素", "环境因素", "激素水平", "病毒感染"],
    "treatment": ["人工泪液", "唾液替代品", "糖皮质激素", "免疫抑制剂", "生物制剂", "对症治疗"],
    "precautions": ["保持口腔卫生", "避免干燥环境", "多喝水", "定期随访", "监测内脏功能", "预防感染"],
    "severity": "chronic",
    "department": "风湿免疫科/皮肤科",
    "common_population": ["中年女性", "女性多于男性（9:1）", "40-50岁", "有家族史者"],
    "related_diseases": ["系统性红斑狼疮", "类风湿关节炎", "硬皮病", "桥本甲状腺炎"]
  },
  {
    "disease_name": "白塞病",
    "aliases": ["Behçet's disease", "BD", "贝赫切特病"],
    "overview": "白塞病是一种以口腔溃疡、生殖器溃疡、眼炎及皮肤损害为主要表现的慢性全身性血管炎症性疾病。",
    "symptoms": ["口腔溃疡", "生殖器溃疡", "眼部炎症", "皮肤结节红斑", "针刺反应阳性", "关节痛", "消化道溃疡"],
    "causes": ["遗传因素", "免疫异常", "感染因素", "环境因素", "炎症反应", "血管炎"],
    "treatment": ["糖皮质激素", "免疫抑制剂", "生物制剂", "对症治疗", "支持治疗", "局部治疗"],
    "precautions": ["避免感染", "避免针刺", "注意口腔卫生", "定期随访", "监测眼部和内脏功能", "避免劳累"],
    "severity": "moderate_to_severe",
    "department": "风湿免疫科/皮肤科",
    "common_population": ["20-40岁", "男性多于女性", "地中海沿岸国家", "东亚国家"],
    "related_diseases": ["系统性红斑狼疮", "结节性红斑", "溃疡性结肠炎", "类风湿关节炎"]
  },
  {
    "disease_name": "天疱疮",
    "aliases": ["pemphigus", "寻常型天疱疮"],
    "overview": "天疱疮是一组由表皮细胞松解引起的自身免疫性大疱性皮肤病，表现为皮肤和黏膜上的松弛性水疱和大疱，易破裂形成糜烂。",
    "symptoms": ["松弛性水疱", "大疱", "糜烂", "尼氏征阳性", "口腔黏膜损害", "瘙痒", "疼痛"],
    "causes": ["自身免疫异常", "遗传因素", "药物因素", "感染因素", "环境因素", "肿瘤相关性"],
    "treatment": ["系统使用糖皮质激素", "免疫抑制剂", "生物制剂（利妥昔单抗）", "支持治疗", "局部治疗", "预防感染"],
    "precautions": ["避免搔抓", "保持皮肤清洁", "预防感染", "定期随访", "监测药物副作用", "加强营养"],
    "severity": "severe",
    "department": "皮肤科",
    "common_population": ["中年人（40-60岁）", "男性和女性发病率相近", "有家族史者", "肿瘤患者"],
    "related_diseases": ["类天疱疮", "疱疹样皮炎", "大疱性表皮松解症", "副肿瘤性天疱疮"]
  },
  {
    "disease_name": "大疱性类天疱疮",
    "aliases": ["bullous pemphigoid", "BP", "类天疱疮"],
    "overview": "大疱性类天疱疮是一种好发于老年人的自身免疫性大疱性皮肤病，表现为紧张性水疱和大疱，尼氏征阴性，预后较好。",
    "symptoms": ["紧张性水疱", "大疱", "瘙痒", "红斑", "尼氏征阴性", "黏膜损害（较少）", "好发于四肢屈侧"],
    "causes": ["自身免疫异常", "遗传因素", "药物因素", "感染因素", "紫外线照射", "肿瘤相关性"],
    "treatment": ["系统使用糖皮质激素", "免疫抑制剂", "生物制剂", "支持治疗", "局部治疗", "预防感染"],
    "precautions": ["避免搔抓", "保持皮肤清洁", "预防感染", "定期随访", "监测药物副作用", "加强营养"],
    "severity": "moderate",
    "department": "皮肤科",
    "common_population": ["老年人（60岁以上）", "男性和女性发病率相近", "有家族史者", "肿瘤患者"],
    "related_diseases": ["天疱疮", "疱疹样皮炎", "妊娠疱疹", "线状IgA大疱性皮肤病"]
  },
  {
    "disease_name": "疱疹样皮炎",
    "aliases": ["dermatitis herpetiformis", "DH", "疱疹样脓疱病"],
    "overview": "疱疹样皮炎是一种与谷蛋白敏感性肠病相关的自身免疫性大疱性皮肤病，表现为群集性水疱，伴有剧烈瘙痒。",
    "symptoms": ["群集性水疱", "剧烈瘙痒", "红斑", "丘疹", "好发于四肢伸侧", "尼氏征阴性", "谷蛋白敏感性"],
    "causes": ["谷蛋白敏感性", "自身免疫异常", "遗传因素", "肠道疾病", "HLA-DQ2/DQ8基因", "环境因素"],
    "treatment": ["无谷蛋白饮食", "氨苯砜", "磺胺类药物", "抗组胺药", "外用糖皮质激素", "对症治疗"],
    "precautions": ["严格无谷蛋白饮食", "避免搔抓", "定期随访", "监测肠道功能", "预防感染", "补充钙和维生素D"],
    "severity": "chronic",
    "department": "皮肤科",
    "common_population": ["成年人（20-40岁）", "男性多于女性", "有家族史者", "谷蛋白敏感者"],
    "related_diseases": ["乳糜泻", "天疱疮", "类天疱疮", "大疱性表皮松解症"]
  },
  {
    "disease_name": "脂溢性角化病",
    "aliases": ["老年疣", "seborrheic keratosis", "基底细胞乳头状瘤"],
    "overview": "脂溢性角化病是一种常见的良性皮肤肿瘤，好发于中老年人，表现为淡褐色至黑色的扁平丘疹或斑块，表面粗糙。",
    "symptoms": ["淡褐色至黑色丘疹", "表面粗糙", "油腻性鳞屑", "好发于面部、手背", "缓慢生长", "无自觉症状"],
    "causes": ["皮肤老化", "遗传因素", "日晒", "病毒感染", "环境因素", "年龄增长"],
    "treatment": ["冷冻治疗", "激光治疗", "电灼治疗", "刮除术", "外用药物", "观察随访"],
    "precautions": ["避免日晒", "定期检查", "避免搔抓", "保持皮肤清洁", "注意观察变化", "避免刺激"],
    "severity": "benign",
    "department": "皮肤科",
    "common_population": ["中老年人", "40岁以上", "有家族史者", "长期日晒者"],
    "related_diseases": ["日光性角化病", "基底细胞癌", "黑色素痣", "鳞状细胞癌"]
  },
  {
    "disease_name": "色素痣",
    "aliases": ["黑痣", "melanocytic nevus", "痣细胞痣"],
    "overview": "色素痣是由痣细胞组成的良性新生物，是最常见的皮肤良性肿瘤，表现为褐色或黑色的斑点、丘疹或结节。",
    "symptoms": ["褐色或黑色斑点", "丘疹或结节", "边界清楚", "表面光滑", "无自觉症状", "大小不一"],
    "causes": ["遗传因素", "胚胎发育", "日晒", "激素水平", "环境因素", "细胞突变"],
    "treatment": ["观察随访", "手术切除", "激光治疗", "冷冻治疗", "电灼治疗", "化学剥脱"],
    "precautions": ["避免搔抓", "避免刺激", "定期检查", "注意观察变化", "避免日晒", "避免摩擦"],
    "severity": "benign",
    "department": "皮肤科",
    "common_population": ["各年龄段", "出生时或儿童期出现", "有家族史者", "皮肤较白者"],
    "related_diseases": ["黑色素瘤", "蓝痣", "Spitz痣", "先天性巨痣"]
  },
  {
    "disease_name": "基底细胞癌",
    "aliases": ["basal cell carcinoma", "BCC", "基底细胞瘤"],
    "overview": "基底细胞癌是最常见的皮肤恶性肿瘤，好发于老年人的曝光部位，表现为珍珠样丘疹或斑块，生长缓慢，转移率低。",
    "symptoms": ["珍珠样丘疹", "边缘隆起", "中央溃疡", "毛细血管扩张", "缓慢生长", "无自觉症状", "好发于面部"],